screen_pilot_mcp/__init__.py
screen_pilot_mcp/action_sequence.py
screen_pilot_mcp/base_tool.py
screen_pilot_mcp/config.py
screen_pilot_mcp/element.py
screen_pilot_mcp/keyboard.py
screen_pilot_mcp/mouse.py
screen_pilot_mcp/screen_capture.py
screen_pilot_mcp/scroll.py
screen_pilot_mcp/server.py
screen_pilot_mcp/utils.py
screen_pilot_mcp-0.1.1.dist-info/licenses/LICENSE
screen_pilot_mcp-0.1.1.dist-info/METADATA
screen_pilot_mcp-0.1.1.dist-info/WHEEL
screen_pilot_mcp-0.1.1.dist-info/entry_points.txt
screen_pilot_mcp-0.1.1.dist-info/top_level.txt
screen_pilot_mcp-0.1.1.dist-info/RECORD
