Metadata-Version: 2.4
Name: screen-pilot-mcp
Version: 0.1.1
Summary: ScreenPilot MCP server for screen automation
Author-email: Knight5128 <liujz_5128@163.com>
Project-URL: Homepage, https://github.com/Knight5128/screen-pilot-mcp
Project-URL: Original ScreenPilot, https://github.com/Mtehabism/ScreenPilot
Requires-Python: >=3.10
License-File: LICENSE
Requires-Dist: annotated-types>=0.7.0
Requires-Dist: anyio>=4.8.0
Requires-Dist: certifi>=2025.1.31
Requires-Dist: charset-normalizer>=3.4.1
Requires-Dist: click>=8.1.8
Requires-Dist: colorama>=0.4.6
Requires-Dist: h11>=0.14.0
Requires-Dist: httpcore>=1.0.7
Requires-Dist: httpx>=0.28.1
Requires-Dist: httpx-sse>=0.4.0
Requires-Dist: idna>=3.10
Requires-Dist: markdown-it-py>=3.0.0
Requires-Dist: mcp>=1.6.0
Requires-Dist: mdurl>=0.1.2
Requires-Dist: MouseInfo>=0.1.3
Requires-Dist: pillow>=11.1.0
Requires-Dist: PyAutoGUI>=0.9.54
Requires-Dist: pydantic>=2.10.0
Requires-Dist: pydantic-settings>=2.8.0
Requires-Dist: PyGetWindow>=0.0.9
Requires-Dist: Pygments>=2.19.1
Requires-Dist: PyMsgBox>=1.0.9
Requires-Dist: pyperclip>=1.9.0
Requires-Dist: PyRect>=0.2.0
Requires-Dist: PyScreeze>=1.0.1
Requires-Dist: python-dotenv>=1.0.0
Requires-Dist: pytweening>=1.2.0
Requires-Dist: requests>=2.32.0
Requires-Dist: rich>=14.0.0
Requires-Dist: shellingham>=1.5.4
Requires-Dist: sniffio>=1.3.1
Requires-Dist: sse-starlette>=2.2.1
Requires-Dist: starlette>=0.46.0
Requires-Dist: typer>=0.15.0
Requires-Dist: typing-inspection>=0.4.0
Requires-Dist: typing_extensions>=4.12.0
Requires-Dist: urllib3>=2.3.0
Requires-Dist: uvicorn>=0.34.0
Dynamic: license-file
